{"cameraMode":{"drawMode":0,"name":"Shaded","section":"Shading Mode"},"sceneLighting":true,"audioPlay":false,"sceneViewState":{"showFog":true,"showMaterialUpdate":false,"showSkybox":true,"showFlares":true,"showImageEffects":true,"showParticleSystems":true},"in2DMode":false,"pivot":{"x":11.221454620361329,"y":-3.829418420791626,"z":-12.269379615783692},"rotation":{"x":-0.33101093769073489,"y":-0.6513543725013733,"z":0.3801625967025757,"w":-0.567138135433197},"size":39.466270446777347,"orthographic":false}